dcmp/__init__.py
dcmp/cli.py
dcmp/predictor.py
dcmp/utils.py
model/mlp_9998.pkl
model/mlp_agm_9993.pkl
dcmp-0.1.3.dist-info/LICENSE
dcmp-0.1.3.dist-info/METADATA
dcmp-0.1.3.dist-info/WHEEL
dcmp-0.1.3.dist-info/entry_points.txt
dcmp-0.1.3.dist-info/top_level.txt
dcmp-0.1.3.dist-info/RECORD
