Metadata-Version: 2.1
Name: dcmp
Version: 0.1.3
Summary: A package to predict DICOM image modalities
Home-page: https://github.com/NeuroGranberg/dcmp
Author: Nima Ch
Author-email: nima.ch@gmail.com
Classifier: Programming Language :: Python :: 3
Classifier: License :: OSI Approved :: MIT License
Classifier: Operating System :: OS Independent
Requires-Python: >=3.6
License-File: LICENSE
Requires-Dist: numpy
Requires-Dist: pydicom
Requires-Dist: opencv-python
Requires-Dist: scikit-learn ==1.4.0
Requires-Dist: joblib
